fcrypter/__init__.py
fcrypter/aes.py
fcrypter/cli.py
fcrypter/fcrypter.py
fcrypter-0.1.1.dist-info/DESCRIPTION.rst
fcrypter-0.1.1.dist-info/METADATA
fcrypter-0.1.1.dist-info/RECORD
fcrypter-0.1.1.dist-info/WHEEL
fcrypter-0.1.1.dist-info/entry_points.txt
fcrypter-0.1.1.dist-info/metadata.json
fcrypter-0.1.1.dist-info/top_level.txt
