Metadata-Version: 2.0
Name: fcrypter
Version: 0.1.1
Summary: File encryption made simple
Home-page: https://github.com/ioparaskev/fcrypter
Author: John Paraskevopoulos
Author-email: ioparaskev@gmail.com
License: GNU General Public License v3
Keywords: fcrypter
Platform: UNKNOWN
Classifier: Development Status :: 2 - Pre-Alpha
Classifier: Intended Audience :: Developers
Classifier: License :: OSI Approved :: GNU General Public License v3 (GPLv3)
Classifier: Natural Language :: English
Classifier: Programming Language :: Python :: 2.7
Classifier: Programming Language :: Python :: 3
Classifier: Programming Language :: Python :: 3.3
Classifier: Programming Language :: Python :: 3.4
Classifier: Programming Language :: Python :: 3.5
Requires-Dist: Click (>=6.0)
Requires-Dist: pycryptodome
